Metadata-Version: 1.0
Name: cha-distributions
Version: 0.1
Summary: Gaussian and Binomial distributions
Home-page: UNKNOWN
Author: Charith Atapattu
Author-email: UNKNOWN
License: UNKNOWN
Platform: UNKNOWN
